{"tabs":[{"tabname":"Details","views":[{"spacing":12,"class":"DepictionSpacerView"},{"class":"DepictionButtonView","text":"Click here to buy me a coffee :)","action":"https:\/\/qr.alipay.com\/fkx16005vrem50fhc8jdye3","yPadding":10},{"title":"Description","class":"DepictionHeaderView"},{"markdown":"Quickly clean up all red badge on desktop via Control Center, Support iOS15+","class":"DepictionMarkdownView"},{"title":"Info","class":"DepictionHeaderView"},{"title":"Version","text":"1.2-6","class":"DepictionTableTextView"},{"title":"Developer","text":"Netskao","class":"DepictionTableTextView"},{"title":"Twitter","action":"https:\/\/twitter.com\/Netskao","class":"DepictionTableButtonView"},{"class":"DepictionTableButtonView","title":"Telegram","action":"https:\/\/t.me\/IPAPatch"}],"class":"DepictionStackView"},{"tabname":"Changes","views":[{"class":"DepictionLayerView","views":[{"useBoldText":true,"title":"1.2-6","class":"DepictionSubheaderView","alignment":0},{"title":"2024-10-20","alignment":2,"class":"DepictionSubheaderView"}]},{"class":"DepictionMarkdownView","useSpacing":true,"markdown":"Initial update"},{"spacing":12,"class":"DepictionSpacerView"}],"class":"DepictionStackView"}],"minVersion":"0.4","headerImage":"https:\/\/comment.sinaimg.cn\/96\/56\/7cdd187bcda4d1e99b1211f2a69e605ee241.jpg","class":"DepictionTabView","tintColor":"#47afd1"}
