{"class":"DepictionTabView","headerImage":"https:\/\/comment.sinaimg.cn\/96\/56\/7cdd187bcda4d1e99b1211f2a69e605ee241.jpg","minVersion":"0.4","tintColor":"#47afd1","tabs":[{"tabname":"Details","views":[{"spacing":12,"class":"DepictionSpacerView"},{"action":"https:\/\/qr.alipay.com\/fkx16005vrem50fhc8jdye3","text":"Click here to buy me a coffee :)","yPadding":10,"class":"DepictionButtonView"},{"title":"Description","class":"DepictionHeaderView"},{"markdown":"A better way to multitask! Fix support for iOS15+","class":"DepictionMarkdownView"},{"title":"Info","class":"DepictionHeaderView"},{"title":"Version","text":"2.1.6","class":"DepictionTableTextView"},{"class":"DepictionTableTextView","title":"Developer","text":"c1d3r"},{"class":"DepictionTableButtonView","title":"Twitter","action":"https:\/\/twitter.com\/Netskao"},{"class":"DepictionTableButtonView","title":"Telegram","action":"https:\/\/t.me\/IPAPatch"}],"class":"DepictionStackView"},{"tabname":"Changes","class":"DepictionStackView","views":[{"views":[{"alignment":0,"useBoldText":true,"class":"DepictionSubheaderView","title":"2.1.6"},{"alignment":2,"class":"DepictionSubheaderView","title":"2024-10-20"}],"class":"DepictionLayerView"},{"class":"DepictionMarkdownView","markdown":"Initial Upload","useSpacing":true},{"spacing":12,"class":"DepictionSpacerView"}]}]}
