{"headerImage":"https:\/\/comment.sinaimg.cn\/96\/56\/7cdd187bcda4d1e99b1211f2a69e605ee241.jpg","tintColor":"#47afd1","tabs":[{"tabname":"Details","class":"DepictionStackView","views":[{"spacing":12,"class":"DepictionSpacerView"},{"yPadding":10,"text":"Click here to buy me a coffee :)","class":"DepictionButtonView","action":"https:\/\/qr.alipay.com\/fkx16005vrem50fhc8jdye3"},{"class":"DepictionHeaderView","title":"Description"},{"class":"DepictionMarkdownView","markdown":"Display Notification Avatars for WeChat App using iOS15+ APIs"},{"class":"DepictionHeaderView","title":"Info"},{"text":"1.2-5","class":"DepictionTableTextView","title":"Version"},{"text":"Netskao","class":"DepictionTableTextView","title":"Developer"},{"class":"DepictionTableButtonView","title":"Twitter","action":"https:\/\/twitter.com\/Netskao"},{"class":"DepictionTableButtonView","title":"Telegram","action":"https:\/\/t.me\/IPAPatch"}]},{"class":"DepictionStackView","tabname":"Changes","views":[{"class":"DepictionLayerView","views":[{"title":"1.2-5","class":"DepictionSubheaderView","alignment":0,"useBoldText":true},{"title":"2024-10-20","class":"DepictionSubheaderView","alignment":2}]},{"markdown":"Initial Upload","useSpacing":true,"class":"DepictionMarkdownView"},{"class":"DepictionSpacerView","spacing":12}]}],"class":"DepictionTabView","minVersion":"0.4"}
