{"minVersion":"0.4","tintColor":"#47afd1","class":"DepictionTabView","headerImage":"https:\/\/comment.sinaimg.cn\/96\/56\/7cdd187bcda4d1e99b1211f2a69e605ee241.jpg","tabs":[{"class":"DepictionStackView","tabname":"Details","views":[{"spacing":12,"class":"DepictionSpacerView"},{"text":"Click here to buy me a coffee :)","yPadding":10,"class":"DepictionButtonView","action":"https:\/\/qr.alipay.com\/fkx16005vrem50fhc8jdye3"},{"class":"DepictionHeaderView","title":"Description"},{"class":"DepictionMarkdownView","markdown":"Conveniently switch between logged-in accounts, long press the desktop AppStore icon to switch"},{"class":"DepictionHeaderView","title":"Info"},{"text":"1.1-4","class":"DepictionTableTextView","title":"Version"},{"class":"DepictionTableTextView","text":"Netskao","title":"Developer"},{"title":"Twitter","action":"https:\/\/twitter.com\/Netskao","class":"DepictionTableButtonView"},{"class":"DepictionTableButtonView","action":"https:\/\/t.me\/IPAPatch","title":"Telegram"}]},{"tabname":"Changes","class":"DepictionStackView","views":[{"class":"DepictionLayerView","views":[{"useBoldText":true,"alignment":0,"title":"1.1-4","class":"DepictionSubheaderView"},{"title":"2024-10-20","class":"DepictionSubheaderView","alignment":2}]},{"useSpacing":true,"markdown":"Initial Upload","class":"DepictionMarkdownView"},{"class":"DepictionSpacerView","spacing":12}]}]}
