{"tabs":[{"views":[{"spacing":12,"class":"DepictionSpacerView"},{"text":"Click here to buy me a coffee :)","action":"https:\/\/qr.alipay.com\/fkx16005vrem50fhc8jdye3","yPadding":10,"class":"DepictionButtonView"},{"class":"DepictionHeaderView","title":"Description"},{"markdown":"Quickly enable or disable Wake on Lift from Control Center, Support iOS15+","class":"DepictionMarkdownView"},{"class":"DepictionHeaderView","title":"Info"},{"text":"1.1-1","class":"DepictionTableTextView","title":"Version"},{"text":"Netskao","title":"Developer","class":"DepictionTableTextView"},{"action":"https:\/\/twitter.com\/Netskao","title":"Twitter","class":"DepictionTableButtonView"},{"action":"https:\/\/t.me\/IPAPatch","title":"Telegram","class":"DepictionTableButtonView"}],"class":"DepictionStackView","tabname":"Details"},{"tabname":"Changes","views":[{"class":"DepictionLayerView","views":[{"alignment":0,"class":"DepictionSubheaderView","useBoldText":true,"title":"1.1-1"},{"alignment":2,"class":"DepictionSubheaderView","title":"2024-10-20"}]},{"class":"DepictionMarkdownView","markdown":"Initial Upload","useSpacing":true},{"class":"DepictionSpacerView","spacing":12}],"class":"DepictionStackView"}],"minVersion":"0.4","class":"DepictionTabView","headerImage":"https:\/\/comment.sinaimg.cn\/96\/56\/7cdd187bcda4d1e99b1211f2a69e605ee241.jpg","tintColor":"#47afd1"}
